<?xml version="1.0" encoding="utf-8" standalone="yes"?>
<Gesture Name="triangle-1" Subject="197Afb" NumPts="601" ScreenWidth="1080" ScreenHeight="1872">
	<Stroke index="1 duration="5479.0">
		<Point X="495" Y="469" T="3277937" P="0.60723007" S="0.0" Orientation="1.5334322" Tilt="0.235778" />
		<Point X="495" Y="489" T="3277952" P="0.60723007" S="0.0" Orientation="1.5334322" Tilt="0.235778" />
		<Point X="495" Y="489" T="3277955" P="0.60723007" S="0.0" Orientation="1.5334322" Tilt="0.235778" />
		<Point X="491" Y="510" T="3277963" P="0.6888129" S="0.0" Orientation="1.6081604" Tilt="0.235778" />
		<Point X="491" Y="510" T="3277969" P="0.6888129" S="0.0" Orientation="1.6081604" Tilt="0.235778" />
		<Point X="488" Y="527" T="3277979" P="0.6888129" S="0.0" Orientation="1.6081604" Tilt="0.235778" />
		<Point X="483" Y="541" T="3277987" P="0.7127504" S="0.0" Orientation="1.6911552" Tilt="0.21970655" />
		<Point X="483" Y="541" T="3277988" P="0.7127504" S="0.0" Orientation="1.6911552" Tilt="0.21970655" />
		<Point X="479" Y="556" T="3278002" P="0.7127504" S="0.0" Orientation="1.6911552" Tilt="0.21970655" />
		<Point X="479" Y="556" T="3278005" P="0.7127504" S="0.0" Orientation="1.6911552" Tilt="0.21970655" />
		<Point X="475" Y="571" T="3278013" P="0.75183195" S="0.0" Orientation="1.7013493" Tilt="0.20239046" />
		<Point X="475" Y="571" T="3278018" P="0.75183195" S="0.0" Orientation="1.7013493" Tilt="0.20239046" />
		<Point X="473" Y="584" T="3278029" P="0.75183195" S="0.0" Orientation="1.7013493" Tilt="0.20239046" />
		<Point X="472" Y="595" T="3278038" P="0.81924766" S="0.0" Orientation="1.8057334" Tilt="0.18832575" />
		<Point X="472" Y="595" T="3278038" P="0.81924766" S="0.0" Orientation="1.8057334" Tilt="0.18832575" />
		<Point X="472" Y="604" T="3278052" P="0.81924766" S="0.0" Orientation="1.8057334" Tilt="0.18832575" />
		<Point X="472" Y="604" T="3278055" P="0.81924766" S="0.0" Orientation="1.8057334" Tilt="0.18832575" />
		<Point X="472" Y="612" T="3278063" P="0.89447975" S="0.0" Orientation="1.8940444" Tilt="0.19306415" />
		<Point X="472" Y="612" T="3278068" P="0.89447975" S="0.0" Orientation="1.8940444" Tilt="0.19306415" />
		<Point X="472" Y="617" T="3278079" P="0.89447975" S="0.0" Orientation="1.8940444" Tilt="0.19306415" />
		<Point X="472" Y="620" T="3278088" P="0.925745" S="0.0" Orientation="1.9773474" Tilt="0.1992069" />
		<Point X="472" Y="620" T="3278088" P="0.925745" S="0.0" Orientation="1.9773474" Tilt="0.1992069" />
		<Point X="472" Y="621" T="3278102" P="0.925745" S="0.0" Orientation="1.9773474" Tilt="0.1992069" />
		<Point X="472" Y="621" T="3278105" P="0.925745" S="0.0" Orientation="1.9773474" Tilt="0.1992069" />
		<Point X="472" Y="622" T="3278113" P="0.93404984" S="0.0" Orientation="2.0969157" Tilt="0.19136806" />
		<Point X="472" Y="622" T="3278118" P="0.93404984" S="0.0" Orientation="2.0969157" Tilt="0.19136806" />
		<Point X="471" Y="621" T="3278129" P="0.93404984" S="0.0" Orientation="2.0969157" Tilt="0.19136806" />
		<Point X="471" Y="620" T="3278138" P="0.9609184" S="0.0" Orientation="2.0969157" Tilt="0.19136806" />
		<Point X="471" Y="620" T="3278138" P="0.9609184" S="0.0" Orientation="2.0969157" Tilt="0.19136806" />
		<Point X="471" Y="613" T="3278152" P="0.9609184" S="0.0" Orientation="2.0969157" Tilt="0.19136806" />
		<Point X="471" Y="613" T="3278155" P="0.9609184" S="0.0" Orientation="2.0969157" Tilt="0.19136806" />
		<Point X="472" Y="604" T="3278163" P="0.9780166" S="0.0" Orientation="2.0969157" Tilt="0.19136806" />
		<Point X="472" Y="604" T="3278168" P="0.9780166" S="0.0" Orientation="2.0969157" Tilt="0.19136806" />
		<Point X="473" Y="589" T="3278179" P="0.9780166" S="0.0" Orientation="2.0969157" Tilt="0.19136806" />
		<Point X="473" Y="573" T="3278188" P="0.9931607" S="0.0" Orientation="2.0969157" Tilt="0.19136806" />
		<Point X="473" Y="573" T="3278188" P="0.9931607" S="0.0" Orientation="2.0969157" Tilt="0.19136806" />
		<Point X="472" Y="556" T="3278202" P="0.9931607" S="0.0" Orientation="2.0969157" Tilt="0.19136806" />
		<Point X="472" Y="556" T="3278205" P="0.9931607" S="0.0" Orientation="2.0969157" Tilt="0.19136806" />
		<Point X="470" Y="539" T="3278213" P="0.99853444" S="0.0" Orientation="2.0969157" Tilt="0.19136806" />
		<Point X="470" Y="539" T="3278218" P="0.99853444" S="0.0" Orientation="2.0969157" Tilt="0.19136806" />
		<Point X="469" Y="525" T="3278229" P="0.99853444" S="0.0" Orientation="2.0969157" Tilt="0.19136806" />
		<Point X="469" Y="510" T="3278238" P="1.0" S="0.0" Orientation="2.0969157" Tilt="0.19136806" />
		<Point X="469" Y="510" T="3278238" P="1.0" S="0.0" Orientation="2.0969157" Tilt="0.19136806" />
		<Point X="470" Y="493" T="3278252" P="1.0" S="0.0" Orientation="2.0969157" Tilt="0.19136806" />
		<Point X="470" Y="493" T="3278255" P="1.0" S="0.0" Orientation="2.0969157" Tilt="0.19136806" />
		<Point X="471" Y="477" T="3278263" P="1.0" S="0.0" Orientation="2.0549834" Tilt="0.20662852" />
		<Point X="471" Y="477" T="3278268" P="1.0" S="0.0" Orientation="2.0549834" Tilt="0.20662852" />
		<Point X="472" Y="460" T="3278279" P="1.0" S="0.0" Orientation="2.0549834" Tilt="0.20662852" />
		<Point X="473" Y="445" T="3278288" P="1.0" S="0.0" Orientation="2.0549834" Tilt="0.20662852" />
		<Point X="473" Y="445" T="3278288" P="1.0" S="0.0" Orientation="2.0549834" Tilt="0.20662852" />
		<Point X="474" Y="432" T="3278302" P="1.0" S="0.0" Orientation="2.0549834" Tilt="0.20662852" />
		<Point X="474" Y="432" T="3278305" P="1.0" S="0.0" Orientation="2.0549834" Tilt="0.20662852" />
		<Point X="475" Y="419" T="3278313" P="1.0" S="0.0" Orientation="2.0549834" Tilt="0.20662852" />
		<Point X="475" Y="419" T="3278318" P="1.0" S="0.0" Orientation="2.0549834" Tilt="0.20662852" />
		<Point X="475" Y="408" T="3278329" P="1.0" S="0.0" Orientation="2.0549834" Tilt="0.20662852" />
		<Point X="475" Y="398" T="3278338" P="1.0" S="0.0" Orientation="2.0549834" Tilt="0.20662852" />
		<Point X="475" Y="398" T="3278338" P="1.0" S="0.0" Orientation="2.0549834" Tilt="0.20662852" />
		<Point X="474" Y="391" T="3278352" P="1.0" S="0.0" Orientation="2.0549834" Tilt="0.20662852" />
		<Point X="474" Y="391" T="3278355" P="1.0" S="0.0" Orientation="2.0549834" Tilt="0.20662852" />
		<Point X="474" Y="387" T="3278363" P="1.0" S="0.0" Orientation="2.0549834" Tilt="0.20662852" />
		<Point X="474" Y="387" T="3278368" P="1.0" S="0.0" Orientation="2.0549834" Tilt="0.20662852" />
		<Point X="474" Y="385" T="3278379" P="1.0" S="0.0" Orientation="2.0549834" Tilt="0.20662852" />
		<Point X="473" Y="384" T="3278388" P="1.0" S="0.0" Orientation="2.0189242" Tilt="0.22220753" />
		<Point X="473" Y="384" T="3278388" P="1.0" S="0.0" Orientation="2.0189242" Tilt="0.22220753" />
		<Point X="473" Y="384" T="3278402" P="1.0" S="0.0" Orientation="2.0189242" Tilt="0.22220753" />
		<Point X="473" Y="384" T="3278405" P="1.0" S="0.0" Orientation="2.0189242" Tilt="0.22220753" />
		<Point X="473" Y="384" T="3278413" P="1.0" S="0.0" Orientation="2.0189242" Tilt="0.22220753" />
		<Point X="473" Y="384" T="3278418" P="1.0" S="0.0" Orientation="2.0189242" Tilt="0.22220753" />
		<Point X="473" Y="384" T="3278429" P="1.0" S="0.0" Orientation="2.0189242" Tilt="0.22220753" />
		<Point X="473" Y="384" T="3278438" P="1.0" S="0.0" Orientation="2.0189242" Tilt="0.22220753" />
		<Point X="473" Y="384" T="3278438" P="1.0" S="0.0" Orientation="2.0189242" Tilt="0.22220753" />
		<Point X="473" Y="385" T="3278452" P="1.0" S="0.0" Orientation="2.0189242" Tilt="0.22220753" />
		<Point X="473" Y="385" T="3278455" P="1.0" S="0.0" Orientation="2.0189242" Tilt="0.22220753" />
		<Point X="473" Y="385" T="3278463" P="1.0" S="0.0" Orientation="2.0189242" Tilt="0.22220753" />
		<Point X="473" Y="385" T="3278468" P="1.0" S="0.0" Orientation="2.0189242" Tilt="0.22220753" />
		<Point X="473" Y="385" T="3278479" P="1.0" S="0.0" Orientation="2.0189242" Tilt="0.22220753" />
		<Point X="473" Y="385" T="3278488" P="1.0" S="0.0" Orientation="2.0189242" Tilt="0.22220753" />
		<Point X="473" Y="385" T="3278488" P="1.0" S="0.0" Orientation="2.0189242" Tilt="0.22220753" />
		<Point X="473" Y="385" T="3278502" P="1.0" S="0.0" Orientation="2.0189242" Tilt="0.22220753" />
		<Point X="473" Y="385" T="3278505" P="1.0" S="0.0" Orientation="2.0189242" Tilt="0.22220753" />
		<Point X="473" Y="384" T="3278513" P="1.0" S="0.0" Orientation="2.0189242" Tilt="0.22220753" />
		<Point X="473" Y="384" T="3278518" P="1.0" S="0.0" Orientation="2.0189242" Tilt="0.22220753" />
		<Point X="473" Y="384" T="3278529" P="1.0" S="0.0" Orientation="2.0189242" Tilt="0.22220753" />
		<Point X="473" Y="384" T="3278538" P="1.0" S="0.0" Orientation="2.0189242" Tilt="0.22220753" />
		<Point X="473" Y="384" T="3278538" P="1.0" S="0.0" Orientation="2.0189242" Tilt="0.22220753" />
		<Point X="473" Y="384" T="3278552" P="1.0" S="0.0" Orientation="2.0189242" Tilt="0.22220753" />
		<Point X="473" Y="384" T="3278555" P="1.0" S="0.0" Orientation="2.0189242" Tilt="0.22220753" />
		<Point X="474" Y="384" T="3278563" P="1.0" S="0.0" Orientation="2.0189242" Tilt="0.22220753" />
		<Point X="474" Y="384" T="3278568" P="1.0" S="0.0" Orientation="2.0189242" Tilt="0.22220753" />
		<Point X="473" Y="383" T="3278579" P="1.0" S="0.0" Orientation="2.0189242" Tilt="0.22220753" />
		<Point X="473" Y="382" T="3278588" P="1.0" S="0.0" Orientation="2.0189242" Tilt="0.22220753" />
		<Point X="473" Y="382" T="3278589" P="1.0" S="0.0" Orientation="2.0189242" Tilt="0.22220753" />
		<Point X="473" Y="379" T="3278602" P="1.0" S="0.0" Orientation="2.0189242" Tilt="0.22220753" />
		<Point X="473" Y="379" T="3278605" P="1.0" S="0.0" Orientation="2.0189242" Tilt="0.22220753" />
		<Point X="473" Y="376" T="3278613" P="1.0" S="0.0" Orientation="2.0189242" Tilt="0.22220753" />
		<Point X="473" Y="376" T="3278618" P="1.0" S="0.0" Orientation="2.0189242" Tilt="0.22220753" />
		<Point X="473" Y="373" T="3278629" P="1.0" S="0.0" Orientation="2.0189242" Tilt="0.22220753" />
		<Point X="472" Y="369" T="3278638" P="1.0" S="0.0" Orientation="2.0189242" Tilt="0.22220753" />
		<Point X="472" Y="369" T="3278638" P="1.0" S="0.0" Orientation="2.0189242" Tilt="0.22220753" />
		<Point X="471" Y="365" T="3278652" P="1.0" S="0.0" Orientation="2.0189242" Tilt="0.22220753" />
		<Point X="471" Y="365" T="3278655" P="1.0" S="0.0" Orientation="2.0189242" Tilt="0.22220753" />
		<Point X="470" Y="360" T="3278663" P="1.0" S="0.0" Orientation="2.0189242" Tilt="0.22220753" />
		<Point X="470" Y="360" T="3278668" P="1.0" S="0.0" Orientation="2.0189242" Tilt="0.22220753" />
		<Point X="469" Y="357" T="3278679" P="1.0" S="0.0" Orientation="2.0189242" Tilt="0.22220753" />
		<Point X="468" Y="353" T="3278688" P="1.0" S="0.0" Orientation="2.0189242" Tilt="0.22220753" />
		<Point X="468" Y="353" T="3278689" P="1.0" S="0.0" Orientation="2.0189242" Tilt="0.22220753" />
		<Point X="467" Y="349" T="3278702" P="1.0" S="0.0" Orientation="2.0189242" Tilt="0.22220753" />
		<Point X="467" Y="349" T="3278705" P="1.0" S="0.0" Orientation="2.0189242" Tilt="0.22220753" />
		<Point X="466" Y="345" T="3278713" P="1.0" S="0.0" Orientation="2.0189242" Tilt="0.22220753" />
		<Point X="466" Y="345" T="3278718" P="1.0" S="0.0" Orientation="2.0189242" Tilt="0.22220753" />
		<Point X="465" Y="341" T="3278729" P="1.0" S="0.0" Orientation="2.0189242" Tilt="0.22220753" />
		<Point X="464" Y="338" T="3278738" P="1.0" S="0.0" Orientation="2.0189242" Tilt="0.22220753" />
		<Point X="464" Y="338" T="3278739" P="1.0" S="0.0" Orientation="2.0189242" Tilt="0.22220753" />
		<Point X="464" Y="336" T="3278753" P="1.0" S="0.0" Orientation="2.0189242" Tilt="0.22220753" />
		<Point X="464" Y="336" T="3278755" P="1.0" S="0.0" Orientation="2.0189242" Tilt="0.22220753" />
		<Point X="463" Y="335" T="3278763" P="1.0" S="0.0" Orientation="2.0189242" Tilt="0.22220753" />
		<Point X="463" Y="335" T="3278768" P="1.0" S="0.0" Orientation="2.0189242" Tilt="0.22220753" />
		<Point X="464" Y="334" T="3278779" P="1.0" S="0.0" Orientation="2.0189242" Tilt="0.22220753" />
		<Point X="463" Y="334" T="3278788" P="1.0" S="0.0" Orientation="2.0189242" Tilt="0.22220753" />
		<Point X="463" Y="334" T="3278788" P="1.0" S="0.0" Orientation="2.0189242" Tilt="0.22220753" />
		<Point X="463" Y="334" T="3278803" P="1.0" S="0.0" Orientation="2.0189242" Tilt="0.22220753" />
		<Point X="463" Y="334" T="3278805" P="1.0" S="0.0" Orientation="2.0189242" Tilt="0.22220753" />
		<Point X="463" Y="334" T="3278814" P="1.0" S="0.0" Orientation="2.0189242" Tilt="0.22220753" />
		<Point X="463" Y="334" T="3278819" P="1.0" S="0.0" Orientation="2.0189242" Tilt="0.22220753" />
		<Point X="463" Y="334" T="3278829" P="1.0" S="0.0" Orientation="2.0189242" Tilt="0.22220753" />
		<Point X="463" Y="334" T="3278838" P="1.0" S="0.0" Orientation="2.0189242" Tilt="0.22220753" />
		<Point X="463" Y="334" T="3278838" P="1.0" S="0.0" Orientation="2.0189242" Tilt="0.22220753" />
		<Point X="463" Y="335" T="3278853" P="1.0" S="0.0" Orientation="2.0189242" Tilt="0.22220753" />
		<Point X="463" Y="335" T="3278855" P="1.0" S="0.0" Orientation="2.0189242" Tilt="0.22220753" />
		<Point X="463" Y="335" T="3278864" P="1.0" S="0.0" Orientation="2.0189242" Tilt="0.22220753" />
		<Point X="463" Y="335" T="3278870" P="1.0" S="0.0" Orientation="2.0189242" Tilt="0.22220753" />
		<Point X="463" Y="338" T="3278879" P="1.0" S="0.0" Orientation="2.0189242" Tilt="0.22220753" />
		<Point X="463" Y="342" T="3278888" P="1.0" S="0.0" Orientation="2.0189242" Tilt="0.22220753" />
		<Point X="463" Y="348" T="3278903" P="1.0" S="0.0" Orientation="2.0189242" Tilt="0.22220753" />
		<Point X="463" Y="348" T="3278905" P="1.0" S="0.0" Orientation="2.0189242" Tilt="0.22220753" />
		<Point X="464" Y="354" T="3278914" P="1.0" S="0.0" Orientation="2.0189242" Tilt="0.22220753" />
		<Point X="464" Y="354" T="3278920" P="1.0" S="0.0" Orientation="2.0189242" Tilt="0.22220753" />
		<Point X="465" Y="363" T="3278929" P="1.0" S="0.0" Orientation="2.0189242" Tilt="0.22220753" />
		<Point X="467" Y="372" T="3278938" P="1.0" S="0.0" Orientation="2.0189242" Tilt="0.22220753" />
		<Point X="469" Y="384" T="3278953" P="1.0" S="0.0" Orientation="2.0189242" Tilt="0.22220753" />
		<Point X="469" Y="384" T="3278955" P="1.0" S="0.0" Orientation="2.0189242" Tilt="0.22220753" />
		<Point X="471" Y="395" T="3278964" P="1.0" S="0.0" Orientation="1.9876709" Tilt="0.23804282" />
		<Point X="471" Y="395" T="3278969" P="1.0" S="0.0" Orientation="1.9876709" Tilt="0.23804282" />
		<Point X="474" Y="406" T="3278979" P="1.0" S="0.0" Orientation="1.9876709" Tilt="0.23804282" />
		<Point X="476" Y="416" T="3278988" P="1.0" S="0.0" Orientation="1.9876709" Tilt="0.23804282" />
		<Point X="476" Y="416" T="3278989" P="1.0" S="0.0" Orientation="1.9876709" Tilt="0.23804282" />
		<Point X="478" Y="425" T="3279003" P="1.0" S="0.0" Orientation="1.9876709" Tilt="0.23804282" />
		<Point X="478" Y="425" T="3279005" P="1.0" S="0.0" Orientation="1.9876709" Tilt="0.23804282" />
		<Point X="479" Y="435" T="3279014" P="1.0" S="0.0" Orientation="2.0526934" Tilt="0.24548227" />
		<Point X="480" Y="443" T="3279029" P="1.0" S="0.0" Orientation="2.0526934" Tilt="0.24548227" />
		<Point X="480" Y="450" T="3279038" P="1.0" S="0.0" Orientation="2.0526934" Tilt="0.24548227" />
		<Point X="480" Y="450" T="3279039" P="1.0" S="0.0" Orientation="2.0526934" Tilt="0.24548227" />
		<Point X="480" Y="455" T="3279053" P="1.0" S="0.0" Orientation="2.0526934" Tilt="0.24548227" />
		<Point X="480" Y="458" T="3279064" P="1.0" S="0.0" Orientation="2.0526934" Tilt="0.24548227" />
		<Point X="480" Y="458" T="3279072" P="1.0" S="0.0" Orientation="2.0526934" Tilt="0.24548227" />
		<Point X="480" Y="460" T="3279079" P="1.0" S="0.0" Orientation="2.0526934" Tilt="0.24548227" />
		<Point X="479" Y="462" T="3279088" P="1.0" S="0.0" Orientation="2.0526934" Tilt="0.24548227" />
		<Point X="479" Y="464" T="3279103" P="1.0" S="0.0" Orientation="2.0526934" Tilt="0.24548227" />
		<Point X="479" Y="464" T="3279105" P="1.0" S="0.0" Orientation="2.0526934" Tilt="0.24548227" />
		<Point X="479" Y="465" T="3279114" P="1.0" S="0.0" Orientation="2.0526934" Tilt="0.24548227" />
		<Point X="479" Y="466" T="3279129" P="1.0" S="0.0" Orientation="2.0526934" Tilt="0.24548227" />
		<Point X="479" Y="466" T="3279138" P="1.0" S="0.0" Orientation="2.0526934" Tilt="0.24548227" />
		<Point X="479" Y="466" T="3279139" P="1.0" S="0.0" Orientation="2.0526934" Tilt="0.24548227" />
		<Point X="479" Y="466" T="3279153" P="1.0" S="0.0" Orientation="2.0526934" Tilt="0.24548227" />
		<Point X="479" Y="466" T="3279155" P="1.0" S="0.0" Orientation="2.0526934" Tilt="0.24548227" />
		<Point X="479" Y="466" T="3279164" P="1.0" S="0.0" Orientation="2.0526934" Tilt="0.24548227" />
		<Point X="479" Y="466" T="3279169" P="1.0" S="0.0" Orientation="2.0526934" Tilt="0.24548227" />
		<Point X="479" Y="466" T="3279179" P="1.0" S="0.0" Orientation="2.0526934" Tilt="0.24548227" />
		<Point X="479" Y="466" T="3279188" P="1.0" S="0.0" Orientation="2.0526934" Tilt="0.24548227" />
		<Point X="479" Y="466" T="3279203" P="1.0" S="0.0" Orientation="2.0526934" Tilt="0.24548227" />
		<Point X="479" Y="466" T="3279205" P="1.0" S="0.0" Orientation="2.0526934" Tilt="0.24548227" />
		<Point X="479" Y="466" T="3279214" P="1.0" S="0.0" Orientation="2.1134632" Tilt="0.2538861" />
		<Point X="479" Y="466" T="3279219" P="1.0" S="0.0" Orientation="2.1134632" Tilt="0.2538861" />
		<Point X="479" Y="466" T="3279230" P="1.0" S="0.0" Orientation="2.1134632" Tilt="0.2538861" />
		<Point X="479" Y="466" T="3279238" P="1.0" S="0.0" Orientation="2.1134632" Tilt="0.2538861" />
		<Point X="479" Y="466" T="3279253" P="1.0" S="0.0" Orientation="2.1134632" Tilt="0.2538861" />
		<Point X="479" Y="466" T="3279255" P="1.0" S="0.0" Orientation="2.1134632" Tilt="0.2538861" />
		<Point X="479" Y="466" T="3279264" P="1.0" S="0.0" Orientation="2.1134632" Tilt="0.2538861" />
		<Point X="479" Y="466" T="3279269" P="1.0" S="0.0" Orientation="2.1134632" Tilt="0.2538861" />
		<Point X="479" Y="466" T="3279280" P="1.0" S="0.0" Orientation="2.1134632" Tilt="0.2538861" />
		<Point X="479" Y="466" T="3279288" P="1.0" S="0.0" Orientation="2.1134632" Tilt="0.2538861" />
		<Point X="479" Y="466" T="3279303" P="1.0" S="0.0" Orientation="2.1134632" Tilt="0.2538861" />
		<Point X="479" Y="466" T="3279305" P="1.0" S="0.0" Orientation="2.1134632" Tilt="0.2538861" />
		<Point X="479" Y="466" T="3279314" P="1.0" S="0.0" Orientation="2.1134632" Tilt="0.2538861" />
		<Point X="479" Y="466" T="3279320" P="1.0" S="0.0" Orientation="2.1134632" Tilt="0.2538861" />
		<Point X="479" Y="466" T="3279330" P="1.0" S="0.0" Orientation="2.1134632" Tilt="0.2538861" />
		<Point X="479" Y="466" T="3279338" P="1.0" S="0.0" Orientation="2.1134632" Tilt="0.2538861" />
		<Point X="479" Y="466" T="3279353" P="1.0" S="0.0" Orientation="2.1134632" Tilt="0.2538861" />
		<Point X="479" Y="466" T="3279356" P="1.0" S="0.0" Orientation="2.1134632" Tilt="0.2538861" />
		<Point X="479" Y="465" T="3279364" P="1.0" S="0.0" Orientation="2.1134632" Tilt="0.2538861" />
		<Point X="479" Y="465" T="3279372" P="1.0" S="0.0" Orientation="2.1134632" Tilt="0.2538861" />
		<Point X="479" Y="465" T="3279380" P="1.0" S="0.0" Orientation="2.1134632" Tilt="0.2538861" />
		<Point X="479" Y="463" T="3279388" P="1.0" S="0.0" Orientation="2.1134632" Tilt="0.2538861" />
		<Point X="479" Y="463" T="3279389" P="1.0" S="0.0" Orientation="2.1134632" Tilt="0.2538861" />
		<Point X="479" Y="459" T="3279403" P="1.0" S="0.0" Orientation="2.1134632" Tilt="0.2538861" />
		<Point X="479" Y="459" T="3279405" P="1.0" S="0.0" Orientation="2.1134632" Tilt="0.2538861" />
		<Point X="479" Y="453" T="3279414" P="1.0" S="0.0" Orientation="2.1134632" Tilt="0.2538861" />
		<Point X="478" Y="444" T="3279430" P="1.0" S="0.0" Orientation="2.1134632" Tilt="0.2538861" />
		<Point X="477" Y="433" T="3279438" P="1.0" S="0.0" Orientation="2.1134632" Tilt="0.2538861" />
		<Point X="477" Y="433" T="3279439" P="1.0" S="0.0" Orientation="2.1134632" Tilt="0.2538861" />
		<Point X="476" Y="420" T="3279453" P="1.0" S="0.0" Orientation="2.1134632" Tilt="0.2538861" />
		<Point X="474" Y="406" T="3279464" P="1.0" S="0.0" Orientation="2.1134632" Tilt="0.2538861" />
		<Point X="474" Y="406" T="3279469" P="1.0" S="0.0" Orientation="2.1134632" Tilt="0.2538861" />
		<Point X="472" Y="390" T="3279480" P="1.0" S="0.0" Orientation="2.1134632" Tilt="0.2538861" />
		<Point X="470" Y="375" T="3279488" P="1.0" S="0.0" Orientation="2.1134632" Tilt="0.2538861" />
		<Point X="467" Y="361" T="3279503" P="1.0" S="0.0" Orientation="2.1134632" Tilt="0.2538861" />
		<Point X="467" Y="361" T="3279506" P="1.0" S="0.0" Orientation="2.1134632" Tilt="0.2538861" />
		<Point X="465" Y="348" T="3279514" P="1.0" S="0.0" Orientation="2.1134632" Tilt="0.2538861" />
		<Point X="465" Y="348" T="3279519" P="1.0" S="0.0" Orientation="2.1134632" Tilt="0.2538861" />
		<Point X="463" Y="335" T="3279530" P="1.0" S="0.0" Orientation="2.1134632" Tilt="0.2538861" />
		<Point X="461" Y="323" T="3279538" P="1.0" S="0.0" Orientation="2.1134632" Tilt="0.2538861" />
		<Point X="460" Y="312" T="3279553" P="1.0" S="0.0" Orientation="2.1134632" Tilt="0.2538861" />
		<Point X="460" Y="312" T="3279556" P="1.0" S="0.0" Orientation="2.1134632" Tilt="0.2538861" />
		<Point X="459" Y="302" T="3279564" P="1.0" S="0.0" Orientation="2.1134632" Tilt="0.2538861" />
		<Point X="459" Y="302" T="3279569" P="1.0" S="0.0" Orientation="2.1134632" Tilt="0.2538861" />
		<Point X="460" Y="294" T="3279580" P="1.0" S="0.0" Orientation="2.1134632" Tilt="0.2538861" />
		<Point X="460" Y="287" T="3279588" P="1.0" S="0.0" Orientation="2.1134632" Tilt="0.2538861" />
		<Point X="461" Y="281" T="3279603" P="1.0" S="0.0" Orientation="2.1134632" Tilt="0.2538861" />
		<Point X="461" Y="281" T="3279606" P="1.0" S="0.0" Orientation="2.1134632" Tilt="0.2538861" />
		<Point X="462" Y="276" T="3279614" P="1.0" S="0.0" Orientation="2.1134632" Tilt="0.2538861" />
		<Point X="462" Y="276" T="3279619" P="1.0" S="0.0" Orientation="2.1134632" Tilt="0.2538861" />
		<Point X="464" Y="271" T="3279630" P="1.0" S="0.0" Orientation="2.1134632" Tilt="0.2538861" />
		<Point X="466" Y="267" T="3279638" P="1.0" S="0.0" Orientation="2.1134632" Tilt="0.2538861" />
		<Point X="469" Y="263" T="3279653" P="1.0" S="0.0" Orientation="2.1134632" Tilt="0.2538861" />
		<Point X="469" Y="263" T="3279656" P="1.0" S="0.0" Orientation="2.1134632" Tilt="0.2538861" />
		<Point X="471" Y="259" T="3279664" P="1.0" S="0.0" Orientation="2.0806217" Tilt="0.26894715" />
		<Point X="471" Y="259" T="3279669" P="1.0" S="0.0" Orientation="2.0806217" Tilt="0.26894715" />
		<Point X="473" Y="256" T="3279680" P="1.0" S="0.0" Orientation="2.0806217" Tilt="0.26894715" />
		<Point X="476" Y="254" T="3279689" P="1.0" S="0.0" Orientation="2.0806217" Tilt="0.26894715" />
		<Point X="478" Y="251" T="3279703" P="1.0" S="0.0" Orientation="2.0806217" Tilt="0.26894715" />
		<Point X="480" Y="248" T="3279714" P="1.0" S="0.0" Orientation="2.0806217" Tilt="0.26894715" />
		<Point X="480" Y="248" T="3279719" P="1.0" S="0.0" Orientation="2.0806217" Tilt="0.26894715" />
		<Point X="482" Y="245" T="3279730" P="1.0" S="0.0" Orientation="2.0806217" Tilt="0.26894715" />
		<Point X="484" Y="242" T="3279738" P="1.0" S="0.0" Orientation="2.0806217" Tilt="0.26894715" />
		<Point X="484" Y="242" T="3279739" P="1.0" S="0.0" Orientation="2.0806217" Tilt="0.26894715" />
		<Point X="486" Y="239" T="3279753" P="1.0" S="0.0" Orientation="2.0806217" Tilt="0.26894715" />
		<Point X="488" Y="236" T="3279764" P="1.0" S="0.0" Orientation="2.0806217" Tilt="0.26894715" />
		<Point X="490" Y="233" T="3279780" P="1.0" S="0.0" Orientation="2.0806217" Tilt="0.26894715" />
		<Point X="491" Y="230" T="3279788" P="1.0" S="0.0" Orientation="2.0806217" Tilt="0.26894715" />
		<Point X="491" Y="230" T="3279789" P="1.0" S="0.0" Orientation="2.0806217" Tilt="0.26894715" />
		<Point X="493" Y="227" T="3279803" P="1.0" S="0.0" Orientation="2.0806217" Tilt="0.26894715" />
		<Point X="493" Y="227" T="3279806" P="1.0" S="0.0" Orientation="2.0806217" Tilt="0.26894715" />
		<Point X="495" Y="223" T="3279814" P="1.0" S="0.0" Orientation="2.0806217" Tilt="0.26894715" />
		<Point X="497" Y="220" T="3279830" P="1.0" S="0.0" Orientation="2.0806217" Tilt="0.26894715" />
		<Point X="500" Y="216" T="3279839" P="1.0" S="0.0" Orientation="2.0806217" Tilt="0.26894715" />
		<Point X="502" Y="212" T="3279853" P="1.0" S="0.0" Orientation="2.0806217" Tilt="0.26894715" />
		<Point X="502" Y="212" T="3279856" P="1.0" S="0.0" Orientation="2.0806217" Tilt="0.26894715" />
		<Point X="505" Y="209" T="3279864" P="1.0" S="0.0" Orientation="2.0223105" Tilt="0.2610504" />
		<Point X="505" Y="209" T="3279869" P="1.0" S="0.0" Orientation="2.0223105" Tilt="0.2610504" />
		<Point X="508" Y="205" T="3279880" P="1.0" S="0.0" Orientation="2.0223105" Tilt="0.2610504" />
		<Point X="511" Y="202" T="3279889" P="1.0" S="0.0" Orientation="1.9954165" Tilt="0.27683878" />
		<Point X="514" Y="199" T="3279903" P="1.0" S="0.0" Orientation="1.9954165" Tilt="0.27683878" />
		<Point X="517" Y="195" T="3279914" P="1.0" S="0.0" Orientation="1.9954165" Tilt="0.27683878" />
		<Point X="517" Y="195" T="3279919" P="1.0" S="0.0" Orientation="1.9954165" Tilt="0.27683878" />
		<Point X="520" Y="191" T="3279930" P="1.0" S="0.0" Orientation="1.9954165" Tilt="0.27683878" />
		<Point X="523" Y="188" T="3279939" P="1.0" S="0.0" Orientation="1.9954165" Tilt="0.27683878" />
		<Point X="523" Y="188" T="3279939" P="1.0" S="0.0" Orientation="1.9954165" Tilt="0.27683878" />
		<Point X="526" Y="184" T="3279953" P="1.0" S="0.0" Orientation="1.9954165" Tilt="0.27683878" />
		<Point X="529" Y="181" T="3279964" P="1.0" S="0.0" Orientation="1.9954165" Tilt="0.27683878" />
		<Point X="532" Y="177" T="3279980" P="1.0" S="0.0" Orientation="1.9954165" Tilt="0.27683878" />
		<Point X="535" Y="173" T="3279989" P="1.0" S="0.0" Orientation="1.9954165" Tilt="0.27683878" />
		<Point X="535" Y="173" T="3279989" P="1.0" S="0.0" Orientation="1.9954165" Tilt="0.27683878" />
		<Point X="538" Y="169" T="3280003" P="1.0" S="0.0" Orientation="1.9954165" Tilt="0.27683878" />
		<Point X="540" Y="166" T="3280014" P="1.0" S="0.0" Orientation="1.9954165" Tilt="0.27683878" />
		<Point X="544" Y="163" T="3280030" P="1.0" S="0.0" Orientation="1.9954165" Tilt="0.27683878" />
		<Point X="547" Y="159" T="3280039" P="1.0" S="0.0" Orientation="1.9954165" Tilt="0.27683878" />
		<Point X="547" Y="159" T="3280039" P="1.0" S="0.0" Orientation="1.9954165" Tilt="0.27683878" />
		<Point X="550" Y="156" T="3280053" P="1.0" S="0.0" Orientation="1.9954165" Tilt="0.27683878" />
		<Point X="553" Y="154" T="3280064" P="1.0" S="0.0" Orientation="1.9363887" Tilt="0.2703014" />
		<Point X="556" Y="151" T="3280080" P="1.0" S="0.0" Orientation="1.9363887" Tilt="0.2703014" />
		<Point X="559" Y="149" T="3280089" P="1.0" S="0.0" Orientation="1.9363887" Tilt="0.2703014" />
		<Point X="559" Y="149" T="3280089" P="1.0" S="0.0" Orientation="1.9363887" Tilt="0.2703014" />
		<Point X="563" Y="146" T="3280103" P="1.0" S="0.0" Orientation="1.9363887" Tilt="0.2703014" />
		<Point X="566" Y="143" T="3280114" P="1.0" S="0.0" Orientation="1.9363887" Tilt="0.2703014" />
		<Point X="570" Y="141" T="3280130" P="1.0" S="0.0" Orientation="1.9363887" Tilt="0.2703014" />
		<Point X="574" Y="139" T="3280139" P="1.0" S="0.0" Orientation="1.9363887" Tilt="0.2703014" />
		<Point X="574" Y="139" T="3280139" P="1.0" S="0.0" Orientation="1.9363887" Tilt="0.2703014" />
		<Point X="578" Y="137" T="3280153" P="1.0" S="0.0" Orientation="1.9363887" Tilt="0.2703014" />
		<Point X="582" Y="135" T="3280164" P="1.0" S="0.0" Orientation="1.9363887" Tilt="0.2703014" />
		<Point X="586" Y="134" T="3280180" P="1.0" S="0.0" Orientation="1.9363887" Tilt="0.2703014" />
		<Point X="589" Y="133" T="3280189" P="1.0" S="0.0" Orientation="1.9363887" Tilt="0.2703014" />
		<Point X="589" Y="133" T="3280189" P="1.0" S="0.0" Orientation="1.9363887" Tilt="0.2703014" />
		<Point X="592" Y="131" T="3280203" P="1.0" S="0.0" Orientation="1.9363887" Tilt="0.2703014" />
		<Point X="595" Y="130" T="3280214" P="1.0" S="0.0" Orientation="1.8744645" Tilt="0.26473027" />
		<Point X="598" Y="128" T="3280230" P="1.0" S="0.0" Orientation="1.8744645" Tilt="0.26473027" />
		<Point X="601" Y="126" T="3280239" P="1.0" S="0.0" Orientation="1.8744645" Tilt="0.26473027" />
		<Point X="601" Y="126" T="3280239" P="1.0" S="0.0" Orientation="1.8744645" Tilt="0.26473027" />
		<Point X="604" Y="125" T="3280253" P="1.0" S="0.0" Orientation="1.8744645" Tilt="0.26473027" />
		<Point X="606" Y="124" T="3280264" P="1.0" S="0.0" Orientation="1.8744645" Tilt="0.26473027" />
		<Point X="608" Y="122" T="3280280" P="1.0" S="0.0" Orientation="1.8744645" Tilt="0.26473027" />
		<Point X="610" Y="121" T="3280289" P="1.0" S="0.0" Orientation="1.8744645" Tilt="0.26473027" />
		<Point X="610" Y="121" T="3280289" P="1.0" S="0.0" Orientation="1.8744645" Tilt="0.26473027" />
		<Point X="612" Y="120" T="3280303" P="1.0" S="0.0" Orientation="1.8744645" Tilt="0.26473027" />
		<Point X="613" Y="119" T="3280314" P="1.0" S="0.0" Orientation="1.8744645" Tilt="0.26473027" />
		<Point X="614" Y="118" T="3280330" P="1.0" S="0.0" Orientation="1.8744645" Tilt="0.26473027" />
		<Point X="615" Y="118" T="3280339" P="1.0" S="0.0" Orientation="1.8744645" Tilt="0.26473027" />
		<Point X="615" Y="118" T="3280339" P="1.0" S="0.0" Orientation="1.8744645" Tilt="0.26473027" />
		<Point X="616" Y="118" T="3280353" P="1.0" S="0.0" Orientation="1.8744645" Tilt="0.26473027" />
		<Point X="617" Y="118" T="3280364" P="1.0" S="0.0" Orientation="1.8744645" Tilt="0.26473027" />
		<Point X="617" Y="117" T="3280380" P="1.0" S="0.0" Orientation="1.8744645" Tilt="0.26473027" />
		<Point X="617" Y="117" T="3280389" P="1.0" S="0.0" Orientation="1.8744645" Tilt="0.26473027" />
		<Point X="617" Y="117" T="3280389" P="1.0" S="0.0" Orientation="1.8744645" Tilt="0.26473027" />
		<Point X="617" Y="117" T="3280403" P="1.0" S="0.0" Orientation="1.8744645" Tilt="0.26473027" />
		<Point X="617" Y="117" T="3280415" P="1.0" S="0.0" Orientation="1.8744645" Tilt="0.26473027" />
		<Point X="617" Y="117" T="3280430" P="1.0" S="0.0" Orientation="1.8744645" Tilt="0.26473027" />
		<Point X="617" Y="117" T="3280439" P="1.0" S="0.0" Orientation="1.8744645" Tilt="0.26473027" />
		<Point X="617" Y="117" T="3280439" P="1.0" S="0.0" Orientation="1.8744645" Tilt="0.26473027" />
		<Point X="617" Y="117" T="3280453" P="1.0" S="0.0" Orientation="1.8744645" Tilt="0.26473027" />
		<Point X="617" Y="117" T="3280464" P="1.0" S="0.0" Orientation="1.8744645" Tilt="0.26473027" />
		<Point X="617" Y="117" T="3280480" P="1.0" S="0.0" Orientation="1.8744645" Tilt="0.26473027" />
		<Point X="617" Y="117" T="3280489" P="1.0" S="0.0" Orientation="1.8744645" Tilt="0.26473027" />
		<Point X="617" Y="117" T="3280489" P="1.0" S="0.0" Orientation="1.8744645" Tilt="0.26473027" />
		<Point X="617" Y="117" T="3280504" P="1.0" S="0.0" Orientation="1.8744645" Tilt="0.26473027" />
		<Point X="617" Y="117" T="3280506" P="1.0" S="0.0" Orientation="1.8744645" Tilt="0.26473027" />
		<Point X="617" Y="117" T="3280515" P="1.0" S="0.0" Orientation="1.8744645" Tilt="0.26473027" />
		<Point X="617" Y="117" T="3280530" P="1.0" S="0.0" Orientation="1.8744645" Tilt="0.26473027" />
		<Point X="617" Y="117" T="3280539" P="1.0" S="0.0" Orientation="1.8744645" Tilt="0.26473027" />
		<Point X="617" Y="117" T="3280554" P="1.0" S="0.0" Orientation="1.8744645" Tilt="0.26473027" />
		<Point X="617" Y="117" T="3280556" P="1.0" S="0.0" Orientation="1.8744645" Tilt="0.26473027" />
		<Point X="617" Y="117" T="3280565" P="1.0" S="0.0" Orientation="1.8744645" Tilt="0.26473027" />
		<Point X="617" Y="117" T="3280571" P="1.0" S="0.0" Orientation="1.8744645" Tilt="0.26473027" />
		<Point X="617" Y="117" T="3280580" P="1.0" S="0.0" Orientation="1.8744645" Tilt="0.26473027" />
		<Point X="617" Y="117" T="3280589" P="1.0" S="0.0" Orientation="1.8744645" Tilt="0.26473027" />
		<Point X="617" Y="117" T="3280604" P="1.0" S="0.0" Orientation="1.8744645" Tilt="0.26473027" />
		<Point X="617" Y="117" T="3280615" P="1.0" S="0.0" Orientation="1.8744645" Tilt="0.26473027" />
		<Point X="617" Y="117" T="3280620" P="1.0" S="0.0" Orientation="1.8744645" Tilt="0.26473027" />
		<Point X="617" Y="117" T="3280630" P="1.0" S="0.0" Orientation="1.8744645" Tilt="0.26473027" />
		<Point X="617" Y="117" T="3280639" P="1.0" S="0.0" Orientation="1.8744645" Tilt="0.26473027" />
		<Point X="617" Y="117" T="3280640" P="1.0" S="0.0" Orientation="1.8744645" Tilt="0.26473027" />
		<Point X="617" Y="117" T="3280654" P="1.0" S="0.0" Orientation="1.8744645" Tilt="0.26473027" />
		<Point X="617" Y="117" T="3280665" P="1.0" S="0.0" Orientation="1.8744645" Tilt="0.26473027" />
		<Point X="617" Y="117" T="3280680" P="1.0" S="0.0" Orientation="1.8744645" Tilt="0.26473027" />
		<Point X="617" Y="117" T="3280689" P="1.0" S="0.0" Orientation="1.8744645" Tilt="0.26473027" />
		<Point X="617" Y="117" T="3280689" P="1.0" S="0.0" Orientation="1.8744645" Tilt="0.26473027" />
		<Point X="617" Y="117" T="3280704" P="1.0" S="0.0" Orientation="1.8744645" Tilt="0.26473027" />
		<Point X="617" Y="117" T="3280715" P="1.0" S="0.0" Orientation="1.8744645" Tilt="0.26473027" />
		<Point X="617" Y="117" T="3280730" P="1.0" S="0.0" Orientation="1.8744645" Tilt="0.26473027" />
		<Point X="617" Y="117" T="3280739" P="1.0" S="0.0" Orientation="1.8744645" Tilt="0.26473027" />
		<Point X="617" Y="117" T="3280739" P="1.0" S="0.0" Orientation="1.8744645" Tilt="0.26473027" />
		<Point X="617" Y="117" T="3280754" P="1.0" S="0.0" Orientation="1.8744645" Tilt="0.26473027" />
		<Point X="617" Y="117" T="3280765" P="1.0" S="0.0" Orientation="1.8744645" Tilt="0.26473027" />
		<Point X="617" Y="118" T="3280780" P="1.0" S="0.0" Orientation="1.8744645" Tilt="0.26473027" />
		<Point X="617" Y="118" T="3280789" P="1.0" S="0.0" Orientation="1.8744645" Tilt="0.26473027" />
		<Point X="617" Y="118" T="3280790" P="1.0" S="0.0" Orientation="1.8744645" Tilt="0.26473027" />
		<Point X="617" Y="119" T="3280804" P="1.0" S="0.0" Orientation="1.8744645" Tilt="0.26473027" />
		<Point X="617" Y="120" T="3280815" P="1.0" S="0.0" Orientation="1.8099535" Tilt="0.26018712" />
		<Point X="617" Y="122" T="3280830" P="1.0" S="0.0" Orientation="1.8099535" Tilt="0.26018712" />
		<Point X="618" Y="124" T="3280839" P="1.0" S="0.0" Orientation="1.8099535" Tilt="0.26018712" />
		<Point X="618" Y="124" T="3280840" P="1.0" S="0.0" Orientation="1.8099535" Tilt="0.26018712" />
		<Point X="619" Y="126" T="3280854" P="1.0" S="0.0" Orientation="1.8099535" Tilt="0.26018712" />
		<Point X="619" Y="126" T="3280856" P="1.0" S="0.0" Orientation="1.8099535" Tilt="0.26018712" />
		<Point X="620" Y="128" T="3280865" P="1.0" S="0.0" Orientation="1.8099535" Tilt="0.26018712" />
		<Point X="620" Y="129" T="3280880" P="1.0" S="0.0" Orientation="1.8099535" Tilt="0.26018712" />
		<Point X="621" Y="130" T="3280889" P="1.0" S="0.0" Orientation="1.8099535" Tilt="0.26018712" />
		<Point X="621" Y="130" T="3280904" P="1.0" S="0.0" Orientation="1.8099535" Tilt="0.26018712" />
		<Point X="621" Y="130" T="3280906" P="1.0" S="0.0" Orientation="1.8099535" Tilt="0.26018712" />
		<Point X="621" Y="130" T="3280915" P="1.0" S="0.0" Orientation="1.8099535" Tilt="0.26018712" />
		<Point X="621" Y="130" T="3280930" P="1.0" S="0.0" Orientation="1.8099535" Tilt="0.26018712" />
		<Point X="621" Y="130" T="3280939" P="1.0" S="0.0" Orientation="1.8099535" Tilt="0.26018712" />
		<Point X="621" Y="130" T="3280954" P="1.0" S="0.0" Orientation="1.8099535" Tilt="0.26018712" />
		<Point X="621" Y="130" T="3280956" P="1.0" S="0.0" Orientation="1.8099535" Tilt="0.26018712" />
		<Point X="621" Y="129" T="3280965" P="1.0" S="0.0" Orientation="1.8099535" Tilt="0.26018712" />
		<Point X="621" Y="130" T="3280981" P="1.0" S="0.0" Orientation="1.8099535" Tilt="0.26018712" />
		<Point X="621" Y="130" T="3280989" P="1.0" S="0.0" Orientation="1.8099535" Tilt="0.26018712" />
		<Point X="621" Y="130" T="3281004" P="1.0" S="0.0" Orientation="1.8099535" Tilt="0.26018712" />
		<Point X="621" Y="130" T="3281006" P="1.0" S="0.0" Orientation="1.8099535" Tilt="0.26018712" />
		<Point X="621" Y="130" T="3281015" P="1.0" S="0.0" Orientation="1.8099535" Tilt="0.26018712" />
		<Point X="621" Y="130" T="3281031" P="1.0" S="0.0" Orientation="1.8099535" Tilt="0.26018712" />
		<Point X="621" Y="130" T="3281039" P="1.0" S="0.0" Orientation="1.8099535" Tilt="0.26018712" />
		<Point X="621" Y="130" T="3281054" P="1.0" S="0.0" Orientation="1.8099535" Tilt="0.26018712" />
		<Point X="621" Y="130" T="3281056" P="1.0" S="0.0" Orientation="1.8099535" Tilt="0.26018712" />
		<Point X="621" Y="130" T="3281065" P="1.0" S="0.0" Orientation="1.8099535" Tilt="0.26018712" />
		<Point X="621" Y="130" T="3281081" P="1.0" S="0.0" Orientation="1.8099535" Tilt="0.26018712" />
		<Point X="621" Y="130" T="3281089" P="1.0" S="0.0" Orientation="1.8099535" Tilt="0.26018712" />
		<Point X="621" Y="130" T="3281104" P="1.0" S="0.0" Orientation="1.8099535" Tilt="0.26018712" />
		<Point X="621" Y="130" T="3281106" P="1.0" S="0.0" Orientation="1.8099535" Tilt="0.26018712" />
		<Point X="621" Y="130" T="3281115" P="1.0" S="0.0" Orientation="1.8099535" Tilt="0.26018712" />
		<Point X="621" Y="130" T="3281131" P="1.0" S="0.0" Orientation="1.8099535" Tilt="0.26018712" />
		<Point X="621" Y="130" T="3281139" P="1.0" S="0.0" Orientation="1.8099535" Tilt="0.26018712" />
		<Point X="621" Y="130" T="3281154" P="1.0" S="0.0" Orientation="1.8099535" Tilt="0.26018712" />
		<Point X="621" Y="130" T="3281156" P="1.0" S="0.0" Orientation="1.8099535" Tilt="0.26018712" />
		<Point X="621" Y="130" T="3281165" P="1.0" S="0.0" Orientation="1.8099535" Tilt="0.26018712" />
		<Point X="621" Y="130" T="3281181" P="1.0" S="0.0" Orientation="1.8099535" Tilt="0.26018712" />
		<Point X="621" Y="130" T="3281189" P="1.0" S="0.0" Orientation="1.8099535" Tilt="0.26018712" />
		<Point X="621" Y="130" T="3281204" P="1.0" S="0.0" Orientation="1.8099535" Tilt="0.26018712" />
		<Point X="621" Y="130" T="3281206" P="1.0" S="0.0" Orientation="1.8099535" Tilt="0.26018712" />
		<Point X="621" Y="130" T="3281215" P="1.0" S="0.0" Orientation="1.8099535" Tilt="0.26018712" />
		<Point X="621" Y="130" T="3281231" P="1.0" S="0.0" Orientation="1.8099535" Tilt="0.26018712" />
		<Point X="621" Y="130" T="3281239" P="1.0" S="0.0" Orientation="1.8099535" Tilt="0.26018712" />
		<Point X="621" Y="130" T="3281254" P="1.0" S="0.0" Orientation="1.8099535" Tilt="0.26018712" />
		<Point X="621" Y="130" T="3281256" P="1.0" S="0.0" Orientation="1.8099535" Tilt="0.26018712" />
		<Point X="621" Y="130" T="3281265" P="1.0" S="0.0" Orientation="1.8099535" Tilt="0.26018712" />
		<Point X="621" Y="130" T="3281281" P="1.0" S="0.0" Orientation="1.8099535" Tilt="0.26018712" />
		<Point X="621" Y="130" T="3281289" P="1.0" S="0.0" Orientation="1.8099535" Tilt="0.26018712" />
		<Point X="621" Y="130" T="3281304" P="1.0" S="0.0" Orientation="1.8099535" Tilt="0.26018712" />
		<Point X="621" Y="130" T="3281315" P="1.0" S="0.0" Orientation="1.8099535" Tilt="0.26018712" />
		<Point X="621" Y="130" T="3281320" P="1.0" S="0.0" Orientation="1.8099535" Tilt="0.26018712" />
		<Point X="621" Y="130" T="3281331" P="1.0" S="0.0" Orientation="1.8099535" Tilt="0.26018712" />
		<Point X="621" Y="130" T="3281339" P="1.0" S="0.0" Orientation="1.8099535" Tilt="0.26018712" />
		<Point X="621" Y="130" T="3281354" P="1.0" S="0.0" Orientation="1.8099535" Tilt="0.26018712" />
		<Point X="621" Y="130" T="3281365" P="1.0" S="0.0" Orientation="1.8099535" Tilt="0.26018712" />
		<Point X="621" Y="130" T="3281381" P="1.0" S="0.0" Orientation="1.8099535" Tilt="0.26018712" />
		<Point X="621" Y="130" T="3281389" P="1.0" S="0.0" Orientation="1.8099535" Tilt="0.26018712" />
		<Point X="621" Y="130" T="3281390" P="1.0" S="0.0" Orientation="1.8099535" Tilt="0.26018712" />
		<Point X="621" Y="131" T="3281404" P="1.0" S="0.0" Orientation="1.8099535" Tilt="0.26018712" />
		<Point X="621" Y="131" T="3281407" P="1.0" S="0.0" Orientation="1.8099535" Tilt="0.26018712" />
		<Point X="621" Y="130" T="3281415" P="1.0" S="0.0" Orientation="1.8099535" Tilt="0.26018712" />
		<Point X="622" Y="131" T="3281431" P="1.0" S="0.0" Orientation="1.8099535" Tilt="0.26018712" />
		<Point X="622" Y="131" T="3281439" P="1.0" S="0.0" Orientation="1.8099535" Tilt="0.26018712" />
		<Point X="623" Y="132" T="3281454" P="1.0" S="0.0" Orientation="1.8099535" Tilt="0.26018712" />
		<Point X="623" Y="132" T="3281457" P="1.0" S="0.0" Orientation="1.8099535" Tilt="0.26018712" />
		<Point X="623" Y="132" T="3281465" P="1.0" S="0.0" Orientation="1.8099535" Tilt="0.26018712" />
		<Point X="624" Y="133" T="3281481" P="1.0" S="0.0" Orientation="1.8099535" Tilt="0.26018712" />
		<Point X="624" Y="134" T="3281489" P="1.0" S="0.0" Orientation="1.8099535" Tilt="0.26018712" />
		<Point X="625" Y="136" T="3281504" P="1.0" S="0.0" Orientation="1.8099535" Tilt="0.26018712" />
		<Point X="626" Y="137" T="3281515" P="1.0" S="0.0" Orientation="1.8099535" Tilt="0.26018712" />
		<Point X="626" Y="137" T="3281520" P="1.0" S="0.0" Orientation="1.8099535" Tilt="0.26018712" />
		<Point X="627" Y="139" T="3281531" P="1.0" S="0.0" Orientation="1.8099535" Tilt="0.26018712" />
		<Point X="629" Y="140" T="3281539" P="1.0" S="0.0" Orientation="1.8099535" Tilt="0.26018712" />
		<Point X="630" Y="142" T="3281554" P="1.0" S="0.0" Orientation="1.8099535" Tilt="0.26018712" />
		<Point X="631" Y="144" T="3281565" P="1.0" S="0.0" Orientation="1.8099535" Tilt="0.26018712" />
		<Point X="632" Y="145" T="3281581" P="1.0" S="0.0" Orientation="1.8099535" Tilt="0.26018712" />
		<Point X="634" Y="147" T="3281590" P="1.0" S="0.0" Orientation="1.8099535" Tilt="0.26018712" />
		<Point X="634" Y="147" T="3281590" P="1.0" S="0.0" Orientation="1.8099535" Tilt="0.26018712" />
		<Point X="635" Y="149" T="3281604" P="1.0" S="0.0" Orientation="1.8099535" Tilt="0.26018712" />
		<Point X="635" Y="149" T="3281607" P="1.0" S="0.0" Orientation="1.8099535" Tilt="0.26018712" />
		<Point X="636" Y="151" T="3281615" P="1.0" S="0.0" Orientation="1.8099535" Tilt="0.26018712" />
		<Point X="637" Y="153" T="3281631" P="1.0" S="0.0" Orientation="1.8099535" Tilt="0.26018712" />
		<Point X="638" Y="156" T="3281640" P="1.0" S="0.0" Orientation="1.8099535" Tilt="0.26018712" />
		<Point X="641" Y="159" T="3281654" P="1.0" S="0.0" Orientation="1.8099535" Tilt="0.26018712" />
		<Point X="642" Y="162" T="3281665" P="1.0" S="0.0" Orientation="1.8099535" Tilt="0.26018712" />
		<Point X="642" Y="162" T="3281670" P="1.0" S="0.0" Orientation="1.8099535" Tilt="0.26018712" />
		<Point X="644" Y="166" T="3281681" P="1.0" S="0.0" Orientation="1.8099535" Tilt="0.26018712" />
		<Point X="646" Y="170" T="3281690" P="1.0" S="0.0" Orientation="1.8099535" Tilt="0.26018712" />
		<Point X="649" Y="175" T="3281704" P="1.0" S="0.0" Orientation="1.8099535" Tilt="0.26018712" />
		<Point X="652" Y="180" T="3281715" P="1.0" S="0.0" Orientation="1.8744645" Tilt="0.26473027" />
		<Point X="656" Y="187" T="3281731" P="1.0" S="0.0" Orientation="1.8744645" Tilt="0.26473027" />
		<Point X="660" Y="195" T="3281740" P="1.0" S="0.0" Orientation="1.8950275" Tilt="0.248134" />
		<Point X="660" Y="195" T="3281740" P="1.0" S="0.0" Orientation="1.8950275" Tilt="0.248134" />
		<Point X="665" Y="203" T="3281754" P="1.0" S="0.0" Orientation="1.8950275" Tilt="0.248134" />
		<Point X="669" Y="212" T="3281765" P="1.0" S="0.0" Orientation="1.8950275" Tilt="0.248134" />
		<Point X="675" Y="220" T="3281781" P="1.0" S="0.0" Orientation="1.8950275" Tilt="0.248134" />
		<Point X="681" Y="228" T="3281790" P="1.0" S="0.0" Orientation="1.8950275" Tilt="0.248134" />
		<Point X="686" Y="236" T="3281804" P="1.0" S="0.0" Orientation="1.8950275" Tilt="0.248134" />
		<Point X="686" Y="236" T="3281807" P="1.0" S="0.0" Orientation="1.8950275" Tilt="0.248134" />
		<Point X="691" Y="245" T="3281815" P="1.0" S="0.0" Orientation="1.9876709" Tilt="0.23804282" />
		<Point X="696" Y="254" T="3281831" P="1.0" S="0.0" Orientation="1.9876709" Tilt="0.23804282" />
		<Point X="701" Y="263" T="3281840" P="1.0" S="0.0" Orientation="1.9876709" Tilt="0.23804282" />
		<Point X="707" Y="272" T="3281854" P="1.0" S="0.0" Orientation="1.9876709" Tilt="0.23804282" />
		<Point X="711" Y="282" T="3281865" P="1.0" S="0.0" Orientation="1.9876709" Tilt="0.23804282" />
		<Point X="711" Y="282" T="3281870" P="1.0" S="0.0" Orientation="1.9876709" Tilt="0.23804282" />
		<Point X="717" Y="290" T="3281881" P="1.0" S="0.0" Orientation="1.9876709" Tilt="0.23804282" />
		<Point X="721" Y="300" T="3281890" P="1.0" S="0.0" Orientation="2.0189242" Tilt="0.22220753" />
		<Point X="727" Y="309" T="3281904" P="1.0" S="0.0" Orientation="2.0189242" Tilt="0.22220753" />
		<Point X="731" Y="319" T="3281915" P="1.0" S="0.0" Orientation="2.0189242" Tilt="0.22220753" />
		<Point X="737" Y="328" T="3281931" P="1.0" S="0.0" Orientation="2.0189242" Tilt="0.22220753" />
		<Point X="741" Y="337" T="3281940" P="1.0" S="0.0" Orientation="2.0189242" Tilt="0.22220753" />
		<Point X="741" Y="337" T="3281940" P="1.0" S="0.0" Orientation="2.0189242" Tilt="0.22220753" />
		<Point X="745" Y="345" T="3281954" P="1.0" S="0.0" Orientation="2.0189242" Tilt="0.22220753" />
		<Point X="750" Y="353" T="3281965" P="1.0" S="0.0" Orientation="2.0189242" Tilt="0.22220753" />
		<Point X="753" Y="360" T="3281981" P="1.0" S="0.0" Orientation="2.0189242" Tilt="0.22220753" />
		<Point X="757" Y="368" T="3281990" P="1.0" S="0.0" Orientation="2.0189242" Tilt="0.22220753" />
		<Point X="761" Y="376" T="3282004" P="1.0" S="0.0" Orientation="2.0189242" Tilt="0.22220753" />
		<Point X="761" Y="376" T="3282007" P="1.0" S="0.0" Orientation="2.0189242" Tilt="0.22220753" />
		<Point X="766" Y="384" T="3282015" P="1.0" S="0.0" Orientation="2.0872107" Tilt="0.23017888" />
		<Point X="770" Y="392" T="3282031" P="1.0" S="0.0" Orientation="2.0872107" Tilt="0.23017888" />
		<Point X="774" Y="400" T="3282040" P="1.0" S="0.0" Orientation="2.0872107" Tilt="0.23017888" />
		<Point X="778" Y="408" T="3282054" P="1.0" S="0.0" Orientation="2.0872107" Tilt="0.23017888" />
		<Point X="783" Y="415" T="3282065" P="1.0" S="0.0" Orientation="2.0872107" Tilt="0.23017888" />
		<Point X="783" Y="415" T="3282070" P="1.0" S="0.0" Orientation="2.0872107" Tilt="0.23017888" />
		<Point X="787" Y="424" T="3282081" P="1.0" S="0.0" Orientation="2.0872107" Tilt="0.23017888" />
		<Point X="790" Y="432" T="3282090" P="1.0" S="0.0" Orientation="2.0526934" Tilt="0.24548227" />
		<Point X="794" Y="440" T="3282104" P="1.0" S="0.0" Orientation="2.0526934" Tilt="0.24548227" />
		<Point X="798" Y="448" T="3282115" P="1.0" S="0.0" Orientation="2.1134632" Tilt="0.2538861" />
		<Point X="801" Y="457" T="3282131" P="1.0" S="0.0" Orientation="2.1134632" Tilt="0.2538861" />
		<Point X="804" Y="464" T="3282140" P="1.0" S="0.0" Orientation="2.1134632" Tilt="0.2538861" />
		<Point X="804" Y="464" T="3282140" P="1.0" S="0.0" Orientation="2.1134632" Tilt="0.2538861" />
		<Point X="807" Y="472" T="3282154" P="1.0" S="0.0" Orientation="2.1134632" Tilt="0.2538861" />
		<Point X="811" Y="480" T="3282165" P="1.0" S="0.0" Orientation="2.1134632" Tilt="0.2538861" />
		<Point X="814" Y="489" T="3282181" P="1.0" S="0.0" Orientation="2.1134632" Tilt="0.2538861" />
		<Point X="817" Y="500" T="3282190" P="1.0" S="0.0" Orientation="2.1699622" Tilt="0.26316208" />
		<Point X="821" Y="512" T="3282204" P="1.0" S="0.0" Orientation="2.1699622" Tilt="0.26316208" />
		<Point X="821" Y="512" T="3282207" P="1.0" S="0.0" Orientation="2.1699622" Tilt="0.26316208" />
		<Point X="825" Y="524" T="3282216" P="1.0" S="0.0" Orientation="2.1699622" Tilt="0.26316208" />
		<Point X="829" Y="537" T="3282231" P="1.0" S="0.0" Orientation="2.1699622" Tilt="0.26316208" />
		<Point X="833" Y="549" T="3282240" P="1.0" S="0.0" Orientation="2.2222857" Tilt="0.27322114" />
		<Point X="837" Y="563" T="3282255" P="1.0" S="0.0" Orientation="2.2222857" Tilt="0.27322114" />
		<Point X="842" Y="577" T="3282266" P="1.0" S="0.0" Orientation="2.2222857" Tilt="0.27322114" />
		<Point X="842" Y="577" T="3282271" P="1.0" S="0.0" Orientation="2.2222857" Tilt="0.27322114" />
		<Point X="846" Y="590" T="3282281" P="1.0" S="0.0" Orientation="2.2222857" Tilt="0.27322114" />
		<Point X="849" Y="599" T="3282290" P="1.0" S="0.0" Orientation="2.2222857" Tilt="0.27322114" />
		<Point X="852" Y="605" T="3282305" P="1.0" S="0.0" Orientation="2.2222857" Tilt="0.27322114" />
		<Point X="853" Y="610" T="3282316" P="1.0" S="0.0" Orientation="2.2222857" Tilt="0.27322114" />
		<Point X="854" Y="611" T="3282331" P="1.0" S="0.0" Orientation="2.2222857" Tilt="0.27322114" />
		<Point X="854" Y="611" T="3282340" P="1.0" S="0.0" Orientation="2.2222857" Tilt="0.27322114" />
		<Point X="854" Y="611" T="3282340" P="1.0" S="0.0" Orientation="2.2222857" Tilt="0.27322114" />
		<Point X="854" Y="611" T="3282355" P="1.0" S="0.0" Orientation="2.2222857" Tilt="0.27322114" />
		<Point X="854" Y="611" T="3282366" P="1.0" S="0.0" Orientation="2.2222857" Tilt="0.27322114" />
		<Point X="854" Y="611" T="3282381" P="1.0" S="0.0" Orientation="2.2222857" Tilt="0.27322114" />
		<Point X="854" Y="611" T="3282390" P="1.0" S="0.0" Orientation="2.2222857" Tilt="0.27322114" />
		<Point X="854" Y="611" T="3282405" P="1.0" S="0.0" Orientation="2.2222857" Tilt="0.27322114" />
		<Point X="854" Y="611" T="3282407" P="1.0" S="0.0" Orientation="2.2222857" Tilt="0.27322114" />
		<Point X="854" Y="610" T="3282416" P="1.0" S="0.0" Orientation="2.2222857" Tilt="0.27322114" />
		<Point X="854" Y="609" T="3282431" P="1.0" S="0.0" Orientation="2.2222857" Tilt="0.27322114" />
		<Point X="855" Y="608" T="3282440" P="1.0" S="0.0" Orientation="2.2222857" Tilt="0.27322114" />
		<Point X="855" Y="606" T="3282455" P="1.0" S="0.0" Orientation="2.2222857" Tilt="0.27322114" />
		<Point X="855" Y="603" T="3282466" P="1.0" S="0.0" Orientation="2.2222857" Tilt="0.27322114" />
		<Point X="855" Y="599" T="3282481" P="1.0" S="0.0" Orientation="2.2222857" Tilt="0.27322114" />
		<Point X="854" Y="596" T="3282490" P="1.0" S="0.0" Orientation="2.2222857" Tilt="0.27322114" />
		<Point X="854" Y="596" T="3282491" P="1.0" S="0.0" Orientation="2.2222857" Tilt="0.27322114" />
		<Point X="853" Y="593" T="3282505" P="1.0" S="0.0" Orientation="2.2222857" Tilt="0.27322114" />
		<Point X="852" Y="590" T="3282516" P="1.0" S="0.0" Orientation="2.2222857" Tilt="0.27322114" />
		<Point X="851" Y="587" T="3282531" P="1.0" S="0.0" Orientation="2.2222857" Tilt="0.27322114" />
		<Point X="850" Y="585" T="3282540" P="1.0" S="0.0" Orientation="2.2222857" Tilt="0.27322114" />
		<Point X="848" Y="583" T="3282555" P="1.0" S="0.0" Orientation="2.2222857" Tilt="0.27322114" />
		<Point X="847" Y="582" T="3282566" P="1.0" S="0.0" Orientation="2.2222857" Tilt="0.27322114" />
		<Point X="847" Y="582" T="3282571" P="1.0" S="0.0" Orientation="2.2222857" Tilt="0.27322114" />
		<Point X="845" Y="581" T="3282581" P="1.0" S="0.0" Orientation="2.2222857" Tilt="0.27322114" />
		<Point X="843" Y="581" T="3282590" P="1.0" S="0.0" Orientation="2.2222857" Tilt="0.27322114" />
		<Point X="839" Y="580" T="3282605" P="1.0" S="0.0" Orientation="2.2222857" Tilt="0.27322114" />
		<Point X="835" Y="581" T="3282616" P="1.0" S="0.0" Orientation="2.2222857" Tilt="0.27322114" />
		<Point X="828" Y="582" T="3282631" P="1.0" S="0.0" Orientation="2.2222857" Tilt="0.27322114" />
		<Point X="823" Y="584" T="3282640" P="1.0" S="0.0" Orientation="2.2222857" Tilt="0.27322114" />
		<Point X="816" Y="586" T="3282655" P="1.0" S="0.0" Orientation="2.2222857" Tilt="0.27322114" />
		<Point X="816" Y="586" T="3282657" P="1.0" S="0.0" Orientation="2.2222857" Tilt="0.27322114" />
		<Point X="809" Y="589" T="3282666" P="1.0" S="0.0" Orientation="2.2222857" Tilt="0.27322114" />
		<Point X="809" Y="589" T="3282672" P="1.0" S="0.0" Orientation="2.2222857" Tilt="0.27322114" />
		<Point X="802" Y="592" T="3282681" P="1.0" S="0.0" Orientation="2.2222857" Tilt="0.27322114" />
		<Point X="793" Y="594" T="3282690" P="1.0" S="0.0" Orientation="2.2222857" Tilt="0.27322114" />
		<Point X="785" Y="597" T="3282705" P="1.0" S="0.0" Orientation="2.2222857" Tilt="0.27322114" />
		<Point X="776" Y="601" T="3282716" P="1.0" S="0.0" Orientation="2.2622924" Tilt="0.2596277" />
		<Point X="765" Y="605" T="3282731" P="1.0" S="0.0" Orientation="2.2622924" Tilt="0.2596277" />
		<Point X="755" Y="609" T="3282740" P="1.0" S="0.0" Orientation="2.2622924" Tilt="0.2596277" />
		<Point X="745" Y="612" T="3282755" P="1.0" S="0.0" Orientation="2.2622924" Tilt="0.2596277" />
		<Point X="745" Y="612" T="3282757" P="1.0" S="0.0" Orientation="2.2622924" Tilt="0.2596277" />
		<Point X="733" Y="615" T="3282766" P="1.0" S="0.0" Orientation="2.2087643" Tilt="0.24899289" />
		<Point X="733" Y="615" T="3282771" P="1.0" S="0.0" Orientation="2.2087643" Tilt="0.24899289" />
		<Point X="722" Y="618" T="3282782" P="1.0" S="0.0" Orientation="2.2087643" Tilt="0.24899289" />
		<Point X="711" Y="620" T="3282790" P="1.0" S="0.0" Orientation="2.2087643" Tilt="0.24899289" />
		<Point X="699" Y="622" T="3282805" P="1.0" S="0.0" Orientation="2.2087643" Tilt="0.24899289" />
		<Point X="687" Y="625" T="3282816" P="1.0" S="0.0" Orientation="2.2087643" Tilt="0.24899289" />
		<Point X="676" Y="627" T="3282832" P="1.0" S="0.0" Orientation="2.2087643" Tilt="0.24899289" />
		<Point X="664" Y="630" T="3282840" P="1.0" S="0.0" Orientation="2.2087643" Tilt="0.24899289" />
		<Point X="652" Y="632" T="3282855" P="1.0" S="0.0" Orientation="2.2087643" Tilt="0.24899289" />
		<Point X="652" Y="632" T="3282857" P="1.0" S="0.0" Orientation="2.2087643" Tilt="0.24899289" />
		<Point X="642" Y="634" T="3282866" P="1.0" S="0.0" Orientation="2.2087643" Tilt="0.24899289" />
		<Point X="642" Y="634" T="3282872" P="1.0" S="0.0" Orientation="2.2087643" Tilt="0.24899289" />
		<Point X="632" Y="636" T="3282882" P="1.0" S="0.0" Orientation="2.2087643" Tilt="0.24899289" />
		<Point X="623" Y="637" T="3282890" P="1.0" S="0.0" Orientation="2.2087643" Tilt="0.24899289" />
		<Point X="615" Y="638" T="3282905" P="1.0" S="0.0" Orientation="2.2087643" Tilt="0.24899289" />
		<Point X="606" Y="640" T="3282916" P="1.0" S="0.0" Orientation="2.1134632" Tilt="0.2538861" />
		<Point X="599" Y="641" T="3282932" P="1.0" S="0.0" Orientation="2.1134632" Tilt="0.2538861" />
		<Point X="591" Y="642" T="3282940" P="1.0" S="0.0" Orientation="2.1134632" Tilt="0.2538861" />
		<Point X="584" Y="642" T="3282955" P="1.0" S="0.0" Orientation="2.1134632" Tilt="0.2538861" />
		<Point X="584" Y="642" T="3282958" P="1.0" S="0.0" Orientation="2.1134632" Tilt="0.2538861" />
		<Point X="577" Y="642" T="3282966" P="1.0" S="0.0" Orientation="2.1134632" Tilt="0.2538861" />
		<Point X="577" Y="642" T="3282971" P="1.0" S="0.0" Orientation="2.1134632" Tilt="0.2538861" />
		<Point X="571" Y="643" T="3282982" P="1.0" S="0.0" Orientation="2.1134632" Tilt="0.2538861" />
		<Point X="565" Y="643" T="3282990" P="1.0" S="0.0" Orientation="2.1134632" Tilt="0.2538861" />
		<Point X="559" Y="642" T="3283005" P="1.0" S="0.0" Orientation="2.1134632" Tilt="0.2538861" />
		<Point X="552" Y="641" T="3283016" P="1.0" S="0.0" Orientation="2.1134632" Tilt="0.2538861" />
		<Point X="546" Y="639" T="3283032" P="1.0" S="0.0" Orientation="2.1134632" Tilt="0.2538861" />
		<Point X="539" Y="637" T="3283040" P="1.0" S="0.0" Orientation="2.1134632" Tilt="0.2538861" />
		<Point X="532" Y="635" T="3283055" P="1.0" S="0.0" Orientation="2.1134632" Tilt="0.2538861" />
		<Point X="532" Y="635" T="3283058" P="1.0" S="0.0" Orientation="2.1134632" Tilt="0.2538861" />
		<Point X="526" Y="633" T="3283066" P="1.0" S="0.0" Orientation="2.1134632" Tilt="0.2538861" />
		<Point X="526" Y="633" T="3283072" P="1.0" S="0.0" Orientation="2.1134632" Tilt="0.2538861" />
		<Point X="520" Y="632" T="3283082" P="1.0" S="0.0" Orientation="2.1134632" Tilt="0.2538861" />
		<Point X="515" Y="631" T="3283090" P="1.0" S="0.0" Orientation="2.1134632" Tilt="0.2538861" />
		<Point X="510" Y="631" T="3283105" P="1.0" S="0.0" Orientation="2.1134632" Tilt="0.2538861" />
		<Point X="505" Y="631" T="3283116" P="1.0" S="0.0" Orientation="2.1134632" Tilt="0.2538861" />
		<Point X="502" Y="630" T="3283132" P="1.0" S="0.0" Orientation="2.1134632" Tilt="0.2538861" />
		<Point X="498" Y="630" T="3283140" P="1.0" S="0.0" Orientation="2.1134632" Tilt="0.2538861" />
		<Point X="495" Y="630" T="3283155" P="1.0" S="0.0" Orientation="2.1134632" Tilt="0.2538861" />
		<Point X="495" Y="630" T="3283158" P="1.0" S="0.0" Orientation="2.1134632" Tilt="0.2538861" />
		<Point X="492" Y="631" T="3283166" P="1.0" S="0.0" Orientation="2.0526934" Tilt="0.24548227" />
		<Point X="492" Y="631" T="3283172" P="1.0" S="0.0" Orientation="2.0526934" Tilt="0.24548227" />
		<Point X="490" Y="631" T="3283182" P="1.0" S="0.0" Orientation="2.0526934" Tilt="0.24548227" />
		<Point X="487" Y="633" T="3283190" P="1.0" S="0.0" Orientation="2.0526934" Tilt="0.24548227" />
		<Point X="485" Y="634" T="3283205" P="1.0" S="0.0" Orientation="2.0526934" Tilt="0.24548227" />
		<Point X="482" Y="634" T="3283216" P="1.0" S="0.0" Orientation="2.0526934" Tilt="0.24548227" />
		<Point X="479" Y="635" T="3283232" P="1.0" S="0.0" Orientation="2.0526934" Tilt="0.24548227" />
		<Point X="476" Y="636" T="3283240" P="1.0" S="0.0" Orientation="2.0526934" Tilt="0.24548227" />
		<Point X="473" Y="636" T="3283255" P="1.0" S="0.0" Orientation="2.0526934" Tilt="0.24548227" />
		<Point X="473" Y="636" T="3283258" P="1.0" S="0.0" Orientation="2.0526934" Tilt="0.24548227" />
		<Point X="471" Y="636" T="3283266" P="1.0" S="0.0" Orientation="2.0526934" Tilt="0.24548227" />
		<Point X="471" Y="636" T="3283272" P="1.0" S="0.0" Orientation="2.0526934" Tilt="0.24548227" />
		<Point X="468" Y="637" T="3283282" P="1.0" S="0.0" Orientation="2.0526934" Tilt="0.24548227" />
		<Point X="466" Y="637" T="3283290" P="1.0" S="0.0" Orientation="2.0526934" Tilt="0.24548227" />
		<Point X="464" Y="637" T="3283305" P="1.0" S="0.0" Orientation="2.0526934" Tilt="0.24548227" />
		<Point X="463" Y="637" T="3283316" P="1.0" S="0.0" Orientation="2.0526934" Tilt="0.24548227" />
		<Point X="462" Y="637" T="3283332" P="1.0" S="0.0" Orientation="2.0526934" Tilt="0.24548227" />
		<Point X="460" Y="637" T="3283341" P="1.0" S="0.0" Orientation="2.0526934" Tilt="0.24548227" />
		<Point X="459" Y="637" T="3283355" P="1.0" S="0.0" Orientation="2.0526934" Tilt="0.24548227" />
		<Point X="459" Y="637" T="3283358" P="1.0" S="0.0" Orientation="2.0526934" Tilt="0.24548227" />
		<Point X="459" Y="637" T="3283366" P="0.83146065" S="0.0" Orientation="2.0526934" Tilt="0.24548227" />
		<Point X="459" Y="637" T="3283372" P="0.83146065" S="0.0" Orientation="2.0526934" Tilt="0.24548227" />
		<Point X="458" Y="637" T="3283382" P="0.83146065" S="0.0" Orientation="2.0526934" Tilt="0.24548227" />
		<Point X="458" Y="635" T="3283391" P="0.5232047" S="0.0" Orientation="2.0526934" Tilt="0.24548227" />
		<Point X="459" Y="631" T="3283405" P="0.5232047" S="0.0" Orientation="2.0526934" Tilt="0.24548227" />
		<Point X="459" Y="631" T="3283416" P="0.5232047" S="0.0" Orientation="2.0526934" Tilt="0.24548227" />
	</Stroke>
</Gesture>
