<?xml version="1.0" encoding="utf-8" standalone="yes"?>
<Gesture ScreenHeight ="1094" ScreenWidth="1934" Subject="TC280" Name="Line-6" >
<Stroke index="1">
<Point X="70" Y="497" P="0.5" T="1476726084644"/>
<Point X="81" Y="495" P="0.5" T="1476726084644"/>
<Point X="91" Y="495" P="0.5" T="1476726084644"/>
<Point X="105" Y="493" P="0.5" T="1476726084644"/>
<Point X="119" Y="492" P="0.5" T="1476726084644"/>
<Point X="134" Y="495" P="0.5" T="1476726084644"/>
<Point X="154" Y="491" P="0.5" T="1476726084644"/>
<Point X="177" Y="485" P="0.5" T="1476726084644"/>
<Point X="199" Y="482" P="0.5" T="1476726084644"/>
<Point X="223" Y="476" P="0.5" T="1476726084644"/>
<Point X="248" Y="475" P="0.5" T="1476726084644"/>
<Point X="272" Y="471" P="0.5" T="1476726084644"/>
<Point X="297" Y="469" P="0.5" T="1476726084644"/>
<Point X="322" Y="468" P="0.5" T="1476726084644"/>
<Point X="345" Y="466" P="0.5" T="1476726084644"/>
<Point X="370" Y="466" P="0.5" T="1476726084644"/>
<Point X="393" Y="465" P="0.5" T="1476726084644"/>
<Point X="416" Y="463" P="0.5" T="1476726084644"/>
<Point X="439" Y="462" P="0.5" T="1476726084644"/>
<Point X="464" Y="460" P="0.5" T="1476726084644"/>
<Point X="490" Y="460" P="0.5" T="1476726084644"/>
<Point X="514" Y="459" P="0.5" T="1476726084644"/>
<Point X="541" Y="458" P="0.5" T="1476726084644"/>
<Point X="566" Y="457" P="0.5" T="1476726084644"/>
<Point X="592" Y="456" P="0.5" T="1476726084644"/>
<Point X="617" Y="454" P="0.5" T="1476726084644"/>
<Point X="643" Y="452" P="0.5" T="1476726084644"/>
<Point X="670" Y="453" P="0.5" T="1476726084644"/>
<Point X="696" Y="453" P="0.5" T="1476726084644"/>
<Point X="722" Y="454" P="0.5" T="1476726084644"/>
<Point X="750" Y="454" P="0.5" T="1476726084644"/>
<Point X="780" Y="457" P="0.5" T="1476726084644"/>
<Point X="808" Y="459" P="0.5" T="1476726084644"/>
<Point X="835" Y="461" P="0.5" T="1476726084644"/>
<Point X="862" Y="464" P="0.5" T="1476726084644"/>
<Point X="888" Y="468" P="0.5" T="1476726084644"/>
<Point X="912" Y="471" P="0.5" T="1476726084644"/>
<Point X="940" Y="476" P="0.5" T="1476726084644"/>
<Point X="962" Y="480" P="0.5" T="1476726084644"/>
<Point X="983" Y="485" P="0.5" T="1476726084644"/>
<Point X="1005" Y="488" P="0.5" T="1476726084644"/>
<Point X="1023" Y="493" P="0.5" T="1476726084644"/>
<Point X="1043" Y="498" P="0.5" T="1476726084644"/>
<Point X="1061" Y="501" P="0.5" T="1476726084644"/>
<Point X="1077" Y="508" P="0.5" T="1476726084644"/>
<Point X="1090" Y="509" P="0.5" T="1476726084644"/>
<Point X="1099" Y="514" P="0.5" T="1476726084644"/>
<Point X="1111" Y="516" P="0.5" T="1476726084644"/>
<Point X="1118" Y="518" P="0.5" T="1476726084644"/>
<Point X="1123" Y="520" P="0.5" T="1476726084644"/>
<Point X="1127" Y="522" P="0.5" T="1476726084644"/>
<Point X="1131" Y="522" P="0.5" T="1476726084644"/>
<Point X="1135" Y="524" P="0.5" T="1476726084644"/>
<Point X="1138" Y="525" P="0.5" T="1476726084644"/>
<Point X="1139" Y="525" P="0.5" T="1476726084644"/>
<Point X="1140" Y="526" P="0.5" T="1476726084644"/>
<Point X="1139" Y="525" P="0.5" T="1476726084644"/>
<Point X="1137" Y="525" P="0.5" T="1476726084644"/>
<Point X="1137" Y="526" P="0.5" T="1476726084644"/>
<Point X="1136" Y="525" P="0.5" T="1476726084644"/>
<Point X="1150" Y="534" P="0.5" T="1476726084644"/>
</Stroke>
</Gesture>
