<?xml version="1.0" encoding="utf-8" standalone="yes"?>
<Gesture Name="5-4" Subject="455Cfb" NumPts="114" ScreenWidth="1080" ScreenHeight="1872">
	<Stroke index="1 duration="633.0">
		<Point X="539" Y="183" T="8180359" P="0.24572545" S="0.0" Orientation="-1.0193576" Tilt="0.55389255" />
		<Point X="532" Y="184" T="8180367" P="0.24572545" S="0.0" Orientation="-1.0193576" Tilt="0.55389255" />
		<Point X="526" Y="185" T="8180375" P="0.24816805" S="0.0" Orientation="-1.0338975" Tilt="0.56865275" />
		<Point X="526" Y="185" T="8180375" P="0.24816805" S="0.0" Orientation="-1.0338975" Tilt="0.56865275" />
		<Point X="521" Y="185" T="8180384" P="0.24816805" S="0.0" Orientation="-1.0338975" Tilt="0.56865275" />
		<Point X="518" Y="185" T="8180392" P="0.24816805" S="0.0" Orientation="-1.0338975" Tilt="0.56865275" />
		<Point X="518" Y="185" T="8180392" P="0.24816805" S="0.0" Orientation="-1.0338975" Tilt="0.56865275" />
		<Point X="515" Y="183" T="8180400" P="0.24719101" S="0.0" Orientation="-1.0338975" Tilt="0.56865275" />
		<Point X="512" Y="178" T="8180408" P="0.24572545" S="0.0" Orientation="-1.0338975" Tilt="0.56865275" />
		<Point X="512" Y="178" T="8180409" P="0.24572545" S="0.0" Orientation="-1.0338975" Tilt="0.56865275" />
		<Point X="509" Y="173" T="8180417" P="0.24230582" S="0.0" Orientation="-1.0225719" Tilt="0.59155786" />
		<Point X="505" Y="167" T="8180425" P="0.24132878" S="0.0" Orientation="-1.0225719" Tilt="0.59155786" />
		<Point X="505" Y="167" T="8180426" P="0.24132878" S="0.0" Orientation="-1.0225719" Tilt="0.59155786" />
		<Point X="501" Y="161" T="8180434" P="0.24035174" S="0.0" Orientation="-0.9983868" Tilt="0.5999234" />
		<Point X="497" Y="157" T="8180442" P="0.23986322" S="0.0" Orientation="-0.9983868" Tilt="0.5999234" />
		<Point X="497" Y="157" T="8180442" P="0.23986322" S="0.0" Orientation="-0.9983868" Tilt="0.5999234" />
		<Point X="493" Y="153" T="8180450" P="0.23986322" S="0.0" Orientation="-0.97506684" Tilt="0.60862774" />
		<Point X="489" Y="151" T="8180458" P="0.24035174" S="0.0" Orientation="-0.97506684" Tilt="0.60862774" />
		<Point X="489" Y="151" T="8180459" P="0.24035174" S="0.0" Orientation="-0.97506684" Tilt="0.60862774" />
		<Point X="485" Y="150" T="8180467" P="0.24084026" S="0.0" Orientation="-0.95259875" Tilt="0.6176564" />
		<Point X="482" Y="149" T="8180475" P="0.24084026" S="0.0" Orientation="-0.95259875" Tilt="0.6176564" />
		<Point X="482" Y="149" T="8180476" P="0.24084026" S="0.0" Orientation="-0.95259875" Tilt="0.6176564" />
		<Point X="480" Y="148" T="8180484" P="0.24084026" S="0.0" Orientation="-0.93096584" Tilt="0.62699497" />
		<Point X="478" Y="148" T="8180492" P="0.24035174" S="0.0" Orientation="-0.93096584" Tilt="0.62699497" />
		<Point X="478" Y="148" T="8180492" P="0.24035174" S="0.0" Orientation="-0.93096584" Tilt="0.62699497" />
		<Point X="477" Y="148" T="8180501" P="0.2393747" S="0.0" Orientation="-0.93096584" Tilt="0.62699497" />
		<Point X="477" Y="148" T="8180508" P="0.23497802" S="0.0" Orientation="-0.9101488" Tilt="0.63663" />
		<Point X="477" Y="148" T="8180509" P="0.23497802" S="0.0" Orientation="-0.9101488" Tilt="0.63663" />
		<Point X="478" Y="148" T="8180517" P="0.21983391" S="0.0" Orientation="-0.9101488" Tilt="0.63663" />
		<Point X="479" Y="149" T="8180525" P="0.21446018" S="0.0" Orientation="-0.9101488" Tilt="0.63663" />
		<Point X="479" Y="149" T="8180525" P="0.21446018" S="0.0" Orientation="-0.9101488" Tilt="0.63663" />
		<Point X="480" Y="149" T="8180534" P="0.2076209" S="0.0" Orientation="-0.92474073" Tilt="0.6500699" />
		<Point X="481" Y="151" T="8180542" P="0.20371275" S="0.0" Orientation="-0.92474073" Tilt="0.6500699" />
		<Point X="481" Y="151" T="8180542" P="0.20371275" S="0.0" Orientation="-0.92474073" Tilt="0.6500699" />
		<Point X="482" Y="155" T="8180550" P="0.20371275" S="0.0" Orientation="-0.92474073" Tilt="0.6500699" />
		<Point X="482" Y="159" T="8180558" P="0.20615534" S="0.0" Orientation="-0.92474073" Tilt="0.6500699" />
		<Point X="482" Y="159" T="8180559" P="0.20615534" S="0.0" Orientation="-0.92474073" Tilt="0.6500699" />
		<Point X="481" Y="167" T="8180567" P="0.2100635" S="0.0" Orientation="-0.9453816" Tilt="0.6407044" />
		<Point X="479" Y="176" T="8180575" P="0.21299462" S="0.0" Orientation="-0.9453816" Tilt="0.6407044" />
		<Point X="479" Y="176" T="8180576" P="0.21299462" S="0.0" Orientation="-0.9453816" Tilt="0.6407044" />
		<Point X="477" Y="189" T="8180584" P="0.21592574" S="0.0" Orientation="-0.96680564" Tilt="0.6316335" />
		<Point X="473" Y="203" T="8180592" P="0.21836834" S="0.0" Orientation="-0.96680564" Tilt="0.6316335" />
		<Point X="473" Y="203" T="8180592" P="0.21836834" S="0.0" Orientation="-0.96680564" Tilt="0.6316335" />
		<Point X="470" Y="220" T="8180600" P="0.22032243" S="0.0" Orientation="-0.98902863" Tilt="0.6228702" />
		<Point X="467" Y="234" T="8180608" P="0.22032243" S="0.0" Orientation="-1.0250386" Tilt="0.62906355" />
		<Point X="467" Y="234" T="8180609" P="0.22032243" S="0.0" Orientation="-1.0250386" Tilt="0.62906355" />
		<Point X="464" Y="248" T="8180617" P="0.22032243" S="0.0" Orientation="-1.048575" Tilt="0.6212056" />
		<Point X="461" Y="260" T="8180625" P="0.22129947" S="0.0" Orientation="-1.0729018" Tilt="0.6136907" />
		<Point X="461" Y="260" T="8180625" P="0.22129947" S="0.0" Orientation="-1.0729018" Tilt="0.6136907" />
		<Point X="458" Y="269" T="8180634" P="0.22520763" S="0.0" Orientation="-1.0980209" Tilt="0.6065316" />
		<Point X="456" Y="276" T="8180642" P="0.23253542" S="0.0" Orientation="-1.1347193" Tilt="0.6154263" />
		<Point X="456" Y="276" T="8180642" P="0.23253542" S="0.0" Orientation="-1.1347193" Tilt="0.6154263" />
		<Point X="454" Y="281" T="8180651" P="0.24132878" S="0.0" Orientation="-1.1609243" Tilt="0.60923076" />
		<Point X="452" Y="286" T="8180658" P="0.24670249" S="0.0" Orientation="-1.1878539" Tilt="0.6034201" />
		<Point X="452" Y="286" T="8180659" P="0.24670249" S="0.0" Orientation="-1.1878539" Tilt="0.6034201" />
		<Point X="451" Y="290" T="8180667" P="0.24816805" S="0.0" Orientation="-1.2154883" Tilt="0.59800565" />
		<Point X="450" Y="294" T="8180675" P="0.24816805" S="0.0" Orientation="-1.2438027" Tilt="0.5929984" />
		<Point X="450" Y="294" T="8180676" P="0.24816805" S="0.0" Orientation="-1.2438027" Tilt="0.5929984" />
		<Point X="450" Y="296" T="8180684" P="0.24670249" S="0.0" Orientation="-1.2518913" Tilt="0.609521" />
		<Point X="450" Y="298" T="8180692" P="0.24474841" S="0.0" Orientation="-1.2802266" Tilt="0.6050922" />
		<Point X="450" Y="298" T="8180692" P="0.24474841" S="0.0" Orientation="-1.2802266" Tilt="0.6050922" />
		<Point X="450" Y="298" T="8180701" P="0.23742062" S="0.0" Orientation="-1.3091351" Tilt="0.6010782" />
		<Point X="451" Y="298" T="8180708" P="0.23253542" S="0.0" Orientation="-1.3091351" Tilt="0.6010782" />
		<Point X="451" Y="298" T="8180709" P="0.23253542" S="0.0" Orientation="-1.3091351" Tilt="0.6010782" />
		<Point X="453" Y="296" T="8180717" P="0.23253542" S="0.0" Orientation="-1.3091351" Tilt="0.6010782" />
		<Point X="456" Y="295" T="8180725" P="0.23253542" S="0.0" Orientation="-1.338575" Tilt="0.5974871" />
		<Point X="456" Y="295" T="8180726" P="0.23253542" S="0.0" Orientation="-1.338575" Tilt="0.5974871" />
		<Point X="459" Y="291" T="8180734" P="0.2320469" S="0.0" Orientation="-1.338575" Tilt="0.5974871" />
		<Point X="463" Y="287" T="8180742" P="0.23058134" S="0.0" Orientation="-1.338575" Tilt="0.5974871" />
		<Point X="463" Y="287" T="8180742" P="0.23058134" S="0.0" Orientation="-1.338575" Tilt="0.5974871" />
		<Point X="468" Y="284" T="8180751" P="0.22813874" S="0.0" Orientation="-1.338575" Tilt="0.5974871" />
		<Point X="474" Y="280" T="8180758" P="0.22667319" S="0.0" Orientation="-1.338575" Tilt="0.5974871" />
		<Point X="474" Y="280" T="8180759" P="0.22667319" S="0.0" Orientation="-1.338575" Tilt="0.5974871" />
		<Point X="481" Y="277" T="8180767" P="0.2247191" S="0.0" Orientation="-1.3091351" Tilt="0.6010782" />
		<Point X="487" Y="276" T="8180775" P="0.22374207" S="0.0" Orientation="-1.3023401" Tilt="0.5842473" />
		<Point X="487" Y="276" T="8180776" P="0.22374207" S="0.0" Orientation="-1.3023401" Tilt="0.5842473" />
		<Point X="493" Y="278" T="8180784" P="0.22325355" S="0.0" Orientation="-1.3023401" Tilt="0.5842473" />
		<Point X="499" Y="281" T="8180792" P="0.22325355" S="0.0" Orientation="-1.3324827" Tilt="0.58052266" />
		<Point X="499" Y="281" T="8180792" P="0.22325355" S="0.0" Orientation="-1.3324827" Tilt="0.58052266" />
		<Point X="505" Y="286" T="8180801" P="0.2247191" S="0.0" Orientation="-1.3324827" Tilt="0.58052266" />
		<Point X="509" Y="293" T="8180808" P="0.22618467" S="0.0" Orientation="-1.3324827" Tilt="0.58052266" />
		<Point X="509" Y="293" T="8180809" P="0.22618467" S="0.0" Orientation="-1.3324827" Tilt="0.58052266" />
		<Point X="513" Y="303" T="8180817" P="0.22862726" S="0.0" Orientation="-1.363144" Tilt="0.5772436" />
		<Point X="515" Y="313" T="8180825" P="0.2296043" S="0.0" Orientation="-1.363144" Tilt="0.5772436" />
		<Point X="515" Y="313" T="8180826" P="0.2296043" S="0.0" Orientation="-1.363144" Tilt="0.5772436" />
		<Point X="517" Y="324" T="8180834" P="0.23058134" S="0.0" Orientation="-1.3893758" Tilt="0.557246" />
		<Point X="518" Y="334" T="8180842" P="0.23106986" S="0.0" Orientation="-1.3893758" Tilt="0.557246" />
		<Point X="518" Y="334" T="8180842" P="0.23106986" S="0.0" Orientation="-1.3893758" Tilt="0.557246" />
		<Point X="518" Y="345" T="8180851" P="0.2320469" S="0.0" Orientation="-1.4217485" Tilt="0.5547888" />
		<Point X="516" Y="355" T="8180859" P="0.23253542" S="0.0" Orientation="-1.4217485" Tilt="0.5547888" />
		<Point X="516" Y="355" T="8180859" P="0.23253542" S="0.0" Orientation="-1.4217485" Tilt="0.5547888" />
		<Point X="512" Y="364" T="8180867" P="0.23400098" S="0.0" Orientation="-1.4544841" Tilt="0.552815" />
		<Point X="507" Y="373" T="8180875" P="0.23839766" S="0.0" Orientation="-1.487507" Tilt="0.5513299" />
		<Point X="507" Y="373" T="8180876" P="0.23839766" S="0.0" Orientation="-1.487507" Tilt="0.5513299" />
		<Point X="500" Y="379" T="8180884" P="0.24914509" S="0.0" Orientation="-1.4897913" Tilt="0.5687243" />
		<Point X="492" Y="384" T="8180892" P="0.25793844" S="0.0" Orientation="-1.5221153" Tilt="0.56776977" />
		<Point X="492" Y="384" T="8180892" P="0.25793844" S="0.0" Orientation="-1.5221153" Tilt="0.56776977" />
		<Point X="483" Y="386" T="8180901" P="0.259404" S="0.0" Orientation="-1.5221153" Tilt="0.56776977" />
		<Point X="472" Y="388" T="8180908" P="0.259404" S="0.0" Orientation="-1.5545563" Tilt="0.56729186" />
		<Point X="472" Y="388" T="8180909" P="0.259404" S="0.0" Orientation="-1.5545563" Tilt="0.56729186" />
		<Point X="462" Y="388" T="8180918" P="0.25256473" S="0.0" Orientation="-1.5545563" Tilt="0.56729186" />
		<Point X="450" Y="387" T="8180925" P="0.23986322" S="0.0" Orientation="-1.5549868" Tilt="0.5847428" />
		<Point X="450" Y="387" T="8180926" P="0.23986322" S="0.0" Orientation="-1.5549868" Tilt="0.5847428" />
		<Point X="438" Y="383" T="8180934" P="0.21934539" S="0.0" Orientation="-1.586606" Tilt="0.5847428" />
		<Point X="425" Y="378" T="8180942" P="0.19540791" S="0.0" Orientation="-1.586606" Tilt="0.5847428" />
		<Point X="425" Y="378" T="8180942" P="0.19540791" S="0.0" Orientation="-1.586606" Tilt="0.5847428" />
		<Point X="414" Y="370" T="8180951" P="0.16072302" S="0.0" Orientation="-1.5862021" Tilt="0.6021941" />
		<Point X="404" Y="359" T="8180959" P="0.14264777" S="0.0" Orientation="-1.5862021" Tilt="0.6021941" />
		<Point X="404" Y="359" T="8180959" P="0.14264777" S="0.0" Orientation="-1.5862021" Tilt="0.6021941" />
		<Point X="396" Y="348" T="8180967" P="0.13434294" S="0.0" Orientation="-1.5557698" Tilt="0.61964524" />
		<Point X="390" Y="336" T="8180975" P="0.12994626" S="0.0" Orientation="-1.5257488" Tilt="0.62007207" />
		<Point X="390" Y="336" T="8180976" P="0.12994626" S="0.0" Orientation="-1.5257488" Tilt="0.62007207" />
		<Point X="387" Y="325" T="8180984" P="0.099658035" S="0.0" Orientation="-1.5257488" Tilt="0.62007207" />
		<Point X="387" Y="325" T="8180992" P="0.099658035" S="0.0" Orientation="-1.5257488" Tilt="0.62007207" />
	</Stroke>
</Gesture>
